gdtw/__init__.py
gdtw/gdtw.py
gdtw/gdtwcpp.cpython-311-darwin.so
gdtw/signal.py
gdtw/utils.py
gdtw/warp.py
gdtw-1.1.3.dist-info/LICENSE
gdtw-1.1.3.dist-info/METADATA
gdtw-1.1.3.dist-info/WHEEL
gdtw-1.1.3.dist-info/top_level.txt
gdtw-1.1.3.dist-info/RECORD
