Metadata-Version: 2.1
Name: gdtw
Version: 1.1.3
Summary: General Dynamic Time Warping
Home-page: https://dderiso.github.io/gdtw
Author: Dave Deriso
Author-email: dderiso@alumni.stanford.edu
Project-URL: Bug Tracker, https://github.com/dderiso/gdtw/issues
Classifier: Programming Language :: Python :: 3
Classifier: Programming Language :: C++
Classifier: License :: OSI Approved :: Apache Software License
Classifier: Operating System :: OS Independent
License-File: LICENSE
Requires-Dist: numpy>=1.20.0
